easyjson/__init__.py
easyjson/easyjson.py
easyjson_custom-0.1.dist-info/METADATA
easyjson_custom-0.1.dist-info/WHEEL
easyjson_custom-0.1.dist-info/top_level.txt
easyjson_custom-0.1.dist-info/RECORD
