Metadata-Version: 2.1
Name: easyjson_custom
Version: 0.1
Summary: библиотека easyjson немного упрощает работу с json файлами
Home-page: https://github.com/NoneScripts/easyjson
Author: None scripts
Classifier: Programming Language :: Python :: 3
Classifier: Operating System :: Microsoft :: Windows
Requires-Python: >=3.4
